l2data_feeder/__init__.py
l2data_feeder/slice_feeder.py
l2data_feeder-0.1.0.dist-info/LICENSE
l2data_feeder-0.1.0.dist-info/METADATA
l2data_feeder-0.1.0.dist-info/WHEEL
l2data_feeder-0.1.0.dist-info/top_level.txt
l2data_feeder-0.1.0.dist-info/RECORD
