Metadata-Version: 2.2
Name: l2data-feeder
Version: 0.1.0
Summary: A library for real-time tick-level data slice feed
Author-email: JasonJiang0303 <chinese88+0303@2925.com>
License: MIT
Project-URL: Homepage, https://github.com/JasonJiang0303/l2data-feeder
Project-URL: Bug Tracker, https://github.com/JasonJiang0303/l2data-feeder/issues
Classifier: Programming Language :: Python :: 3
Classifier: License :: OSI Approved :: MIT License
Classifier: Operating System :: OS Independent
Requires-Python: >=3.7
License-File: LICENSE
Requires-Dist: protobuf>=3.12.0
Requires-Dist: l2data-reader>=0.1.4
